{
  "案由": "机动车交通事故责任纠纷",
  "案由编号": "137",
  "version": "1.0",
  "抗辩分类": {
    "权利消灭": [
      {
        "抗辩名称": "已全额赔偿",
        "类型": "权利消灭",
        "法律依据": "《民法典》第560条（债务已经履行）",
        "证明事项": [
          "已向原告支付全部赔偿款",
          "赔偿金额覆盖原告全部合理损失"
        ],
        "证据类型": [
          "赔偿协议",
          "银行转账凭证",
          "收条/收据"
        ],
        "举证方": "被告",
        "难度": "低",
        "备注": "赔偿协议需注意是否包含'一次性了结'条款"
      },
      {
        "抗辩名称": "保险公司已理赔完毕",
        "类型": "权利消灭",
        "法律依据": "《道路交通安全法》第76条、《机动车交通事故责任强制保险条例》",
        "证明事项": [
          "交强险/商业三者险已在限额内全额理赔",
          "保险公司已向原告支付全部赔偿金"
        ],
        "证据类型": [
          "保险理赔计算书",
          "赔款支付凭证",
          "保险合同",
          "理赔结案通知"
        ],
        "举证方": "被告",
        "难度": "低",
        "备注": "保险赔偿不足以覆盖全部损失的，不足部分由侵权人承担"
      },
      {
        "抗辩名称": "超过诉讼时效",
        "类型": "权利消灭",
        "法律依据": "《民法典》第188条（3年诉讼时效）",
        "证明事项": [
          "原告自知道或应当知道权利被侵害之日起超过3年起诉",
          "不存在时效中断、中止事由"
        ],
        "证据类型": [
          "交通事故认定书日期",
          "治疗终结日期",
          "伤残鉴定日期",
          "起诉状日期"
        ],
        "举证方": "被告",
        "难度": "中",
        "备注": "人身损害诉讼时效起算点：知道或应当知道权利被侵害之日（一般为治疗终结日或定残日）"
      },
      {
        "抗辩名称": "双方已达成和解协议并履行完毕",
        "类型": "权利消灭",
        "法律依据": "《民法典》第560条、第562条（合同履行）",
        "证明事项": [
          "双方已签署和解/调解协议",
          "协议已全部履行完毕"
        ],
        "证据类型": [
          "和解协议书",
          "调解协议书",
          "付款凭证",
          "收据"
        ],
        "举证方": "被告",
        "难度": "低",
        "备注": "和解协议显失公平的，受害方可请求撤销（需在1年内）"
      },
      {
        "抗辩名称": "工伤保险已赔付（竞合情形）",
        "类型": "权利消灭",
        "法律依据": "《社会保险法》第42条、《最高人民法院关于审理工伤保险行政案件若干问题的规定》第8条",
        "证明事项": [
          "事故已被认定为工伤",
          "工伤保险基金已支付医疗费等费用",
          "重复主张的项目已由工伤保险覆盖"
        ],
        "证据类型": [
          "工伤认定决定书",
          "工伤保险待遇支付凭证",
          "医疗费发票"
        ],
        "举证方": "被告",
        "难度": "中",
        "备注": "医疗费等实际支出项目不可重复获赔，但伤残赔偿金、精神损害抚慰金可另行主张"
      }
    ],
    "权利妨碍": [
      {
        "抗辩名称": "事故责任划分不当",
        "类型": "权利妨碍",
        "法律依据": "《道路交通安全法》第73条、《道路交通事故处理程序规定》",
        "证明事项": [
          "交通事故认定书认定的责任比例不当",
          "存在应当重新划分责任的事实依据"
        ],
        "证据类型": [
          "事故现场照片",
          "行车记录仪视频",
          "证人证言",
          "事故复核申请书"
        ],
        "举证方": "被告",
        "难度": "高",
        "备注": "事故认定书为证据而非行政行为，法院可依证据综合判断调整责任比例"
      },
      {
        "抗辩名称": "伤残等级过高——申请重新鉴定",
        "类型": "权利妨碍",
        "法律依据": "《民事诉讼法》第81条、《最高人民法院关于民事诉讼证据的若干规定》第40条",
        "证明事项": [
          "原鉴定结论依据不足或程序违法",
          "伤残等级与实际伤情不符"
        ],
        "证据类型": [
          "原鉴定意见书",
          "病历资料",
          "重新鉴定申请书",
          "医学专家意见"
        ],
        "举证方": "被告",
        "难度": "高",
        "备注": "重新鉴定需提供充分理由，法院有裁量权决定是否准许"
      },
      {
        "抗辩名称": "医疗费不合理——非事故关联",
        "类型": "权利妨碍",
        "法律依据": "《民法典》第1179条（赔偿范围限于合理费用）",
        "证明事项": [
          "部分医疗费与本次交通事故无因果关系",
          "存在治疗自身疾病的情况"
        ],
        "证据类型": [
          "病历资料",
          "用药清单",
          "医疗费关联性鉴定意见",
          "既往病史记录"
        ],
        "举证方": "被告",
        "难度": "中",
        "备注": "可申请医疗费关联性鉴定，区分事故所致损伤与自身疾病的治疗费用"
      },
      {
        "抗辩名称": "医疗费不合理——过度治疗",
        "类型": "权利妨碍",
        "法律依据": "《民法典》第1179条、诚实信用原则",
        "证明事项": [
          "存在超出合理必要的医疗检查或治疗",
          "部分费用与伤情严重程度不符"
        ],
        "证据类型": [
          "病历资料",
          "用药清单",
          "同类伤情治疗方案对比",
          "医疗合理性鉴定"
        ],
        "举证方": "被告",
        "难度": "中",
        "备注": "过度治疗的认定需结合伤情、医疗常规综合判断"
      },
      {
        "抗辩名称": "误工期过长",
        "类型": "权利妨碍",
        "法律依据": "《民法典》第1179条、《人身损害误工期评定规范》(GA/T 1193)",
        "证明事项": [
          "原告主张的误工期超出合理范围",
          "原告实际已恢复工作能力"
        ],
        "证据类型": [
          "误工期鉴定意见",
          "工资发放记录",
          "考勤记录",
          "用人单位证明"
        ],
        "举证方": "被告",
        "难度": "中",
        "备注": "误工期一般参照GA/T 1193标准，实际收入未减少的不支持误工费"
      },
      {
        "抗辩名称": "护理依赖程度低",
        "类型": "权利妨碍",
        "法律依据": "《民法典》第1179条、《人身损害护理依赖程度评定》(GB/T 31147)",
        "证明事项": [
          "原告主张的护理依赖程度过高",
          "实际护理需求低于主张标准"
        ],
        "证据类型": [
          "护理依赖鉴定意见",
          "医疗机构护理建议",
          "日常生活能力评估"
        ],
        "举证方": "被告",
        "难度": "中",
        "备注": "护理依赖分完全/大部分/部分三级，需依据专业鉴定确定"
      },
      {
        "抗辩名称": "后续治疗费尚未实际发生",
        "类型": "权利妨碍",
        "法律依据": "《人身损害赔偿司法解释》第6条",
        "证明事项": [
          "后续治疗费仅为预估尚未实际发生",
          "实际发生金额可能与鉴定结论不一致"
        ],
        "证据类型": [
          "后续治疗费鉴定意见",
          "医疗机构证明",
          "实际治疗费用凭证"
        ],
        "举证方": "被告",
        "难度": "低",
        "备注": "后续治疗费可待实际发生后另行起诉"
      }
    ],
    "权利阻止": [
      {
        "抗辩名称": "受害人过错（过失相抵）",
        "类型": "权利阻止",
        "法律依据": "《民法典》第1173条（过失相抵）",
        "证明事项": [
          "受害人对损害的发生或扩大存在过错",
          "应相应减轻赔偿义务人的赔偿责任"
        ],
        "证据类型": [
          "事故认定书",
          "受害人违规行为证据",
          "现场照片/视频",
          "证人证言"
        ],
        "举证方": "被告",
        "难度": "中",
        "备注": "机动车与非机动车/行人事故中，过失相抵适用需特别注意优者危险负担原则"
      },
      {
        "抗辩名称": "不可抗力",
        "类型": "权利阻止",
        "法律依据": "《民法典》第590条、第180条（不可抗力免责）",
        "证明事项": [
          "事故系不可抗力（如地震、山体滑坡等自然灾害）直接导致",
          "已尽合理注意义务仍无法避免"
        ],
        "证据类型": [
          "气象证明",
          "地质灾害证明",
          "政府应急通报",
          "现场照片"
        ],
        "举证方": "被告",
        "难度": "高",
        "备注": "一般天气原因不构成不可抗力，需达到不能预见、不能避免、不能克服的程度"
      },
      {
        "抗辩名称": "紧急避险",
        "类型": "权利阻止",
        "法律依据": "《民法典》第182条（紧急避险）",
        "证明事项": [
          "为避免更大危险采取紧急避险措施",
          "避险行为未超过必要限度"
        ],
        "证据类型": [
          "事故现场证据",
          "行车记录仪视频",
          "证人证言",
          "避险合理性鉴定"
        ],
        "举证方": "被告",
        "难度": "高",
        "备注": "紧急避险引起损害的，由引起险情发生的人承担责任"
      },
      {
        "抗辩名称": "好意同乘减责",
        "类型": "权利阻止",
        "法律依据": "《民法典》第1217条（好意同乘规则）",
        "证明事项": [
          "事故发生在好意同乘过程中",
          "驾驶人非故意或重大过失"
        ],
        "证据类型": [
          "同乘关系证明（朋友/同事/亲属关系）",
          "事故认定书",
          "驾驶人过错程度证据"
        ],
        "举证方": "被告",
        "难度": "中",
        "备注": "好意同乘仅减轻而非免除赔偿责任，驾驶人故意或重大过失的不减责"
      },
      {
        "抗辩名称": "非医保用药费用不赔",
        "类型": "权利阻止",
        "法律依据": "保险合同条款、《保险法》第17条",
        "证明事项": [
          "医疗费中包含非医保目录用药",
          "保险合同约定了非医保用药免赔条款"
        ],
        "证据类型": [
          "保险合同",
          "用药清单",
          "医保目录对照表"
        ],
        "举证方": "被告",
        "难度": "中",
        "备注": "司法实践中对非医保用药免赔条款的效力存在争议，部分法院以格式条款为由不予支持"
      },
      {
        "抗辩名称": "停运损失无依据",
        "类型": "权利阻止",
        "法律依据": "《民法典》第1184条、《道路交通事故损害赔偿司法解释》第12条",
        "证明事项": [
          "原告主张的停运损失缺乏充分证据",
          "停运期间不合理或收入标准缺乏依据"
        ],
        "证据类型": [
          "运营资质证明",
          "营运收入流水",
          "停运时间证明",
          "同类车辆收入标准"
        ],
        "举证方": "被告",
        "难度": "中",
        "备注": "停运损失仅限经营性车辆，需有合法运营资质"
      },
      {
        "抗辩名称": "车辆贬值损失不支持",
        "类型": "权利阻止",
        "法律依据": "最高法司法解释精神、《民法典》第1184条",
        "证明事项": [
          "车辆贬值损失无明确法律依据",
          "司法实践中一般不予支持"
        ],
        "证据类型": [
          "车辆维修记录",
          "车辆评估报告"
        ],
        "举证方": "被告",
        "难度": "低",
        "备注": "最高法倾向不支持车辆贬值损失，但极端情形（新车重大事故）有例外"
      },
      {
        "抗辩名称": "精神损害抚慰金过高",
        "类型": "权利阻止",
        "法律依据": "《民法典》第1183条、《人身损害赔偿司法解释》第5条",
        "证明事项": [
          "原告主张的精神损害抚慰金金额过高",
          "未构成严重精神损害"
        ],
        "证据类型": [
          "伤残等级证明",
          "精神损害鉴定",
          "当地司法实践标准"
        ],
        "举证方": "被告",
        "难度": "中",
        "备注": "精神损害抚慰金需结合过错程度、损害后果、当地生活水平等综合确定"
      },
      {
        "抗辩名称": "被扶养人生活费计算有误",
        "类型": "权利阻止",
        "法律依据": "《人身损害赔偿司法解释》第17条、第28条",
        "证明事项": [
          "被扶养人人数或扶养年限计算有误",
          "存在多个扶养人时未分摊"
        ],
        "证据类型": [
          "被扶养人身份证明",
          "扶养关系证明",
          "其他扶养人信息",
          "户籍信息"
        ],
        "举证方": "被告",
        "难度": "中",
        "备注": "被扶养人有数人的，年赔偿总额累计不超过上一年度人均消费性支出额"
      },
      {
        "抗辩名称": "鉴定程序违法或鉴定机构无资质",
        "类型": "权利阻止",
        "法律依据": "《民事诉讼法》第81条、《司法鉴定程序通则》",
        "证明事项": [
          "鉴定机构无相应鉴定资质",
          "鉴定程序存在违法情形",
          "鉴定意见依据不足"
        ],
        "证据类型": [
          "鉴定机构资质证书",
          "鉴定程序记录",
          "鉴定委托材料",
          "鉴定人资质信息"
        ],
        "举证方": "被告",
        "难度": "高",
        "备注": "鉴定意见存在严重瑕疵的，法院可不予采信或通知鉴定人出庭"
      }
    ]
  }
}